odoo10_addon_product_uom_unece-10.0.1.1.0-py2.7-nspkg.pth
odoo/addons/product_uom_unece/README.rst
odoo/addons/product_uom_unece/__init__.py
odoo/addons/product_uom_unece/__manifest__.py
odoo/addons/product_uom_unece/data/unece.xml
odoo/addons/product_uom_unece/models/__init__.py
odoo/addons/product_uom_unece/models/product_uom.py
odoo/addons/product_uom_unece/views/product_uom.xml
odoo10_addon_product_uom_unece-10.0.1.1.0.dist-info/DESCRIPTION.rst
odoo10_addon_product_uom_unece-10.0.1.1.0.dist-info/METADATA
odoo10_addon_product_uom_unece-10.0.1.1.0.dist-info/RECORD
odoo10_addon_product_uom_unece-10.0.1.1.0.dist-info/WHEEL
odoo10_addon_product_uom_unece-10.0.1.1.0.dist-info/metadata.json
odoo10_addon_product_uom_unece-10.0.1.1.0.dist-info/namespace_packages.txt
odoo10_addon_product_uom_unece-10.0.1.1.0.dist-info/top_level.txt
